plasmid_assessor/Assessment.py
plasmid_assessor/__init__.py
plasmid_assessor/reports.py
plasmid_assessor/report_assets/assessment_report.pug
plasmid_assessor/report_assets/report_style.css
plasmid_assessor/report_assets/imgs/plasma_logo.png
plasmid_assessor-0.2.1.dist-info/licenses/LICENSE
tests/test_Assessment.py
plasmid_assessor-0.2.1.dist-info/METADATA
plasmid_assessor-0.2.1.dist-info/WHEEL
plasmid_assessor-0.2.1.dist-info/top_level.txt
plasmid_assessor-0.2.1.dist-info/RECORD
