Metadata-Version: 2.4
Name: plasmid_assessor
Version: 0.2.1
Summary: Plasmid assessment for Golden Gate cloning
Author: Peter Vegh
License-Expression: MIT
Project-URL: Homepage, https://github.com/Edinburgh-Genome-Foundry/Plasmid_assessor
Keywords: biology,dna
License-File: LICENSE
Requires-Dist: biopython
Requires-Dist: dnacauldron
Requires-Dist: dna_features_viewer
Provides-Extra: report
Requires-Dist: pdf_reports; extra == "report"
Requires-Dist: pandas; extra == "report"
Requires-Dist: matplotlib; extra == "report"
Dynamic: license-file
